package com.twitter.android.platform;

import android.content.Context;
import android.os.AsyncTask;

final class p extends AsyncTask
{
  private final Context a;

  public p(Context paramContext)
  {
    this.a = paramContext;
  }

  // ERROR //
  private java.lang.Void a(java.lang.String[] paramArrayOfString)
  {
    // Byte code:
    //   0: invokestatic 22	java/lang/System:currentTimeMillis	()J
    //   3: lstore_2
    //   4: new 24	java/util/HashMap
    //   7: dup
    //   8: invokespecial 25	java/util/HashMap:<init>	()V
    //   11: astore 4
    //   13: aload_1
    //   14: iconst_0
    //   15: aaload
    //   16: ldc 27
    //   18: invokevirtual 33	java/lang/String:split	(Ljava/lang/String;)[Ljava/lang/String;
    //   21: astore 5
    //   23: aload 5
    //   25: arraylength
    //   26: istore 6
    //   28: iconst_0
    //   29: istore 7
    //   31: iload 7
    //   33: iload 6
    //   35: if_icmpge +42 -> 77
    //   38: aload 5
    //   40: iload 7
    //   42: aaload
    //   43: ldc 35
    //   45: invokevirtual 33	java/lang/String:split	(Ljava/lang/String;)[Ljava/lang/String;
    //   48: astore 22
    //   50: aload 22
    //   52: arraylength
    //   53: iconst_2
    //   54: if_icmpne +17 -> 71
    //   57: aload 4
    //   59: aload 22
    //   61: iconst_0
    //   62: aaload
    //   63: aload 22
    //   65: iconst_1
    //   66: aaload
    //   67: invokevirtual 39	java/util/HashMap:put	(Ljava/lang/Object;Ljava/lang/Object;)Ljava/lang/Object;
    //   70: pop
    //   71: iinc 7 1
    //   74: goto -43 -> 31
    //   77: new 41	java/io/ByteArrayOutputStream
    //   80: dup
    //   81: invokespecial 42	java/io/ByteArrayOutputStream:<init>	()V
    //   84: astore 8
    //   86: new 44	java/io/OutputStreamWriter
    //   89: dup
    //   90: aload 8
    //   92: invokespecial 47	java/io/OutputStreamWriter:<init>	(Ljava/io/OutputStream;)V
    //   95: astore 9
    //   97: getstatic 52	do:a	Lef;
    //   100: aload 9
    //   102: invokevirtual 57	ef:a	(Ljava/io/Writer;)Law;
    //   105: astore 16
    //   107: aload 16
    //   109: invokevirtual 62	aw:c	()V
    //   112: aload 16
    //   114: ldc 64
    //   116: ldc 66
    //   118: invokevirtual 69	aw:a	(Ljava/lang/String;Ljava/lang/String;)V
    //   121: aload 16
    //   123: ldc 71
    //   125: getstatic 77	com/twitter/android/service/j:V	Lcom/twitter/android/service/j;
    //   128: invokevirtual 81	com/twitter/android/service/j:toString	()Ljava/lang/String;
    //   131: invokevirtual 69	aw:a	(Ljava/lang/String;Ljava/lang/String;)V
    //   134: aload 16
    //   136: ldc 83
    //   138: lload_2
    //   139: invokevirtual 86	aw:a	(Ljava/lang/String;J)V
    //   142: aload 16
    //   144: ldc 88
    //   146: iconst_3
    //   147: invokevirtual 91	aw:a	(Ljava/lang/String;I)V
    //   150: aload 16
    //   152: ldc 93
    //   154: aload 4
    //   156: ldc 95
    //   158: invokevirtual 99	java/util/HashMap:get	(Ljava/lang/Object;)Ljava/lang/Object;
    //   161: checkcast 29	java/lang/String
    //   164: invokevirtual 69	aw:a	(Ljava/lang/String;Ljava/lang/String;)V
    //   167: aload 16
    //   169: ldc 101
    //   171: aload 4
    //   173: ldc 103
    //   175: invokevirtual 99	java/util/HashMap:get	(Ljava/lang/Object;)Ljava/lang/Object;
    //   178: checkcast 29	java/lang/String
    //   181: invokevirtual 69	aw:a	(Ljava/lang/String;Ljava/lang/String;)V
    //   184: aload 16
    //   186: ldc 105
    //   188: aload 4
    //   190: ldc 107
    //   192: invokevirtual 99	java/util/HashMap:get	(Ljava/lang/Object;)Ljava/lang/Object;
    //   195: checkcast 29	java/lang/String
    //   198: invokevirtual 69	aw:a	(Ljava/lang/String;Ljava/lang/String;)V
    //   201: aload 4
    //   203: ldc 109
    //   205: invokevirtual 99	java/util/HashMap:get	(Ljava/lang/Object;)Ljava/lang/Object;
    //   208: checkcast 29	java/lang/String
    //   211: astore 18
    //   213: aload 18
    //   215: ifnull +12 -> 227
    //   218: aload 16
    //   220: ldc 111
    //   222: aload 18
    //   224: invokevirtual 69	aw:a	(Ljava/lang/String;Ljava/lang/String;)V
    //   227: aload 4
    //   229: ldc 113
    //   231: invokevirtual 99	java/util/HashMap:get	(Ljava/lang/Object;)Ljava/lang/Object;
    //   234: checkcast 29	java/lang/String
    //   237: astore 19
    //   239: aload 19
    //   241: ifnull +18 -> 259
    //   244: aload 16
    //   246: ldc 115
    //   248: aload 19
    //   250: invokestatic 121	java/lang/Integer:valueOf	(Ljava/lang/String;)Ljava/lang/Integer;
    //   253: invokevirtual 125	java/lang/Integer:intValue	()I
    //   256: invokevirtual 91	aw:a	(Ljava/lang/String;I)V
    //   259: aload 4
    //   261: ldc 127
    //   263: invokevirtual 99	java/util/HashMap:get	(Ljava/lang/Object;)Ljava/lang/Object;
    //   266: checkcast 29	java/lang/String
    //   269: astore 20
    //   271: aload 20
    //   273: ifnull +12 -> 285
    //   276: aload 16
    //   278: ldc 129
    //   280: aload 20
    //   282: invokevirtual 69	aw:a	(Ljava/lang/String;Ljava/lang/String;)V
    //   285: aload 16
    //   287: invokevirtual 132	aw:d	()V
    //   290: aload 16
    //   292: invokevirtual 135	aw:e	()V
    //   295: aload 16
    //   297: invokestatic 140	cr:a	(Ljava/io/Closeable;)V
    //   300: aload 9
    //   302: invokestatic 140	cr:a	(Ljava/io/Closeable;)V
    //   305: aload 8
    //   307: invokestatic 140	cr:a	(Ljava/io/Closeable;)V
    //   310: aload_0
    //   311: getfield 13	com/twitter/android/platform/p:a	Landroid/content/Context;
    //   314: aload 8
    //   316: invokevirtual 144	java/io/ByteArrayOutputStream:toByteArray	()[B
    //   319: invokestatic 149	com/twitter/android/service/ScribeService:a	(Landroid/content/Context;[B)V
    //   322: aconst_null
    //   323: areturn
    //   324: astore 21
    //   326: aconst_null
    //   327: astore 11
    //   329: aconst_null
    //   330: astore 12
    //   332: aload 12
    //   334: invokestatic 140	cr:a	(Ljava/io/Closeable;)V
    //   337: aload 11
    //   339: invokestatic 140	cr:a	(Ljava/io/Closeable;)V
    //   342: aload 8
    //   344: invokestatic 140	cr:a	(Ljava/io/Closeable;)V
    //   347: goto -37 -> 310
    //   350: astore 13
    //   352: aconst_null
    //   353: astore 14
    //   355: aconst_null
    //   356: astore 15
    //   358: aload 15
    //   360: invokestatic 140	cr:a	(Ljava/io/Closeable;)V
    //   363: aload 14
    //   365: invokestatic 140	cr:a	(Ljava/io/Closeable;)V
    //   368: aload 8
    //   370: invokestatic 140	cr:a	(Ljava/io/Closeable;)V
    //   373: aload 13
    //   375: athrow
    //   376: astore 13
    //   378: aload 9
    //   380: astore 14
    //   382: aconst_null
    //   383: astore 15
    //   385: goto -27 -> 358
    //   388: astore 13
    //   390: aload 9
    //   392: astore 14
    //   394: aload 16
    //   396: astore 15
    //   398: goto -40 -> 358
    //   401: astore 10
    //   403: aload 9
    //   405: astore 11
    //   407: aconst_null
    //   408: astore 12
    //   410: goto -78 -> 332
    //   413: astore 17
    //   415: aload 9
    //   417: astore 11
    //   419: aload 16
    //   421: astore 12
    //   423: goto -91 -> 332
    //
    // Exception table:
    //   from	to	target	type
    //   86	97	324	java/io/IOException
    //   86	97	350	finally
    //   97	107	376	finally
    //   107	213	388	finally
    //   218	227	388	finally
    //   227	239	388	finally
    //   244	259	388	finally
    //   259	271	388	finally
    //   276	285	388	finally
    //   285	295	388	finally
    //   97	107	401	java/io/IOException
    //   107	213	413	java/io/IOException
    //   218	227	413	java/io/IOException
    //   227	239	413	java/io/IOException
    //   244	259	413	java/io/IOException
    //   259	271	413	java/io/IOException
    //   276	285	413	java/io/IOException
    //   285	295	413	java/io/IOException
  }
}

/* Location:
 * Qualified Name:     com.twitter.android.platform.p
 * Java Class Version: 6 (50.0)
 * JD-Core Version:    0.6.1-SNAPSHOT
 */
