package android.support.v7.internal.view;

import android.content.Context;
import android.support.v4.view.ActionProvider;
import android.util.AttributeSet;
import android.view.Menu;
import android.view.MenuInflater;
import java.io.IOException;
import org.xmlpull.v1.XmlPullParser;
import org.xmlpull.v1.XmlPullParserException;

public class SupportMenuInflater extends MenuInflater
{
  private static final Class<?>[] ACTION_PROVIDER_CONSTRUCTOR_SIGNATURE = ACTION_VIEW_CONSTRUCTOR_SIGNATURE;
  private static final Class<?>[] ACTION_VIEW_CONSTRUCTOR_SIGNATURE = { Context.class };
  private static final String LOG_TAG = "SupportMenuInflater";
  private static final int NO_ID = 0;
  private static final String XML_GROUP = "group";
  private static final String XML_ITEM = "item";
  private static final String XML_MENU = "menu";
  private final Object[] mActionProviderConstructorArguments;
  private final Object[] mActionViewConstructorArguments;
  private Context mContext;
  private Object mRealOwner;

  public SupportMenuInflater(Context paramContext)
  {
    super(paramContext);
    this.mContext = paramContext;
    this.mRealOwner = paramContext;
    this.mActionViewConstructorArguments = new Object[] { paramContext };
    this.mActionProviderConstructorArguments = this.mActionViewConstructorArguments;
  }

  private void parseMenu(XmlPullParser paramXmlPullParser, AttributeSet paramAttributeSet, Menu paramMenu)
    throws XmlPullParserException, IOException
  {
    SupportMenuInflater.MenuState localMenuState = new SupportMenuInflater.MenuState(this, paramMenu);
    int i = paramXmlPullParser.getEventType();
    int j = 0;
    Object localObject = null;
    String str3;
    label57: int k;
    if (i == 2)
    {
      str3 = paramXmlPullParser.getName();
      if (str3.equals("menu"))
      {
        i = paramXmlPullParser.next();
        k = 0;
        label60: if (k != 0)
          return;
      }
    }
    switch (i)
    {
    default:
    case 2:
    case 3:
      while (true)
      {
        i = paramXmlPullParser.next();
        break label60;
        throw new RuntimeException("Expecting menu, got " + str3);
        i = paramXmlPullParser.next();
        if (i != 1)
          break;
        break label57;
        if (j == 0)
        {
          String str2 = paramXmlPullParser.getName();
          if (str2.equals("group"))
          {
            localMenuState.readGroup(paramAttributeSet);
          }
          else if (str2.equals("item"))
          {
            localMenuState.readItem(paramAttributeSet);
          }
          else if (str2.equals("menu"))
          {
            parseMenu(paramXmlPullParser, paramAttributeSet, localMenuState.addSubMenuItem());
          }
          else
          {
            j = 1;
            localObject = str2;
            continue;
            String str1 = paramXmlPullParser.getName();
            if ((j != 0) && (str1.equals(localObject)))
            {
              j = 0;
              localObject = null;
            }
            else if (str1.equals("group"))
            {
              localMenuState.resetGroup();
            }
            else if (str1.equals("item"))
            {
              if (!localMenuState.hasAddedItem())
                if ((SupportMenuInflater.MenuState.access$000(localMenuState) != null) && (SupportMenuInflater.MenuState.access$000(localMenuState).hasSubMenu()))
                  localMenuState.addSubMenuItem();
                else
                  localMenuState.addItem();
            }
            else if (str1.equals("menu"))
            {
              k = 1;
            }
          }
        }
      }
    case 1:
    }
    throw new RuntimeException("Unexpected end of document");
  }

  // ERROR //
  public void inflate(int paramInt, Menu paramMenu)
  {
    // Byte code:
    //   0: aload_2
    //   1: instanceof 151
    //   4: ifne +10 -> 14
    //   7: aload_0
    //   8: iload_1
    //   9: aload_2
    //   10: invokespecial 153	android/view/MenuInflater:inflate	(ILandroid/view/Menu;)V
    //   13: return
    //   14: aconst_null
    //   15: astore_3
    //   16: aload_0
    //   17: getfield 47	android/support/v7/internal/view/SupportMenuInflater:mContext	Landroid/content/Context;
    //   20: invokevirtual 157	android/content/Context:getResources	()Landroid/content/res/Resources;
    //   23: iload_1
    //   24: invokevirtual 163	android/content/res/Resources:getLayout	(I)Landroid/content/res/XmlResourceParser;
    //   27: astore_3
    //   28: aload_0
    //   29: aload_3
    //   30: aload_3
    //   31: invokestatic 169	android/util/Xml:asAttributeSet	(Lorg/xmlpull/v1/XmlPullParser;)Landroid/util/AttributeSet;
    //   34: aload_2
    //   35: invokespecial 126	android/support/v7/internal/view/SupportMenuInflater:parseMenu	(Lorg/xmlpull/v1/XmlPullParser;Landroid/util/AttributeSet;Landroid/view/Menu;)V
    //   38: aload_3
    //   39: ifnull -26 -> 13
    //   42: aload_3
    //   43: invokeinterface 174 1 0
    //   48: return
    //   49: astore 6
    //   51: new 176	android/view/InflateException
    //   54: dup
    //   55: ldc 178
    //   57: aload 6
    //   59: invokespecial 181	android/view/InflateException:<init>	(Ljava/lang/String;Ljava/lang/Throwable;)V
    //   62: athrow
    //   63: astore 5
    //   65: aload_3
    //   66: ifnull +9 -> 75
    //   69: aload_3
    //   70: invokeinterface 174 1 0
    //   75: aload 5
    //   77: athrow
    //   78: astore 4
    //   80: new 176	android/view/InflateException
    //   83: dup
    //   84: ldc 178
    //   86: aload 4
    //   88: invokespecial 181	android/view/InflateException:<init>	(Ljava/lang/String;Ljava/lang/Throwable;)V
    //   91: athrow
    //
    // Exception table:
    //   from	to	target	type
    //   16	38	49	org/xmlpull/v1/XmlPullParserException
    //   16	38	63	finally
    //   51	63	63	finally
    //   80	92	63	finally
    //   16	38	78	java/io/IOException
  }
}

/* Location:
 * Qualified Name:     android.support.v7.internal.view.SupportMenuInflater
 * Java Class Version: 6 (50.0)
 * JD-Core Version:    0.6.1-SNAPSHOT
 */
