package com.applovin.impl.sdk;

import java.net.Socket;

class an extends ar
{
  private final Socket a;
  private final int b;
  private final String c;
  private final String h;

  public an(int paramInt, AppLovinSdkImpl paramAppLovinSdkImpl, Socket paramSocket)
  {
    this(paramInt, "", "text/html", paramAppLovinSdkImpl, paramSocket);
  }

  public an(int paramInt, String paramString1, String paramString2, AppLovinSdkImpl paramAppLovinSdkImpl, Socket paramSocket)
  {
    super("FinishWebRequest", paramAppLovinSdkImpl);
    this.b = paramInt;
    this.c = paramString1;
    this.h = paramString2;
    this.a = paramSocket;
  }

  // ERROR //
  public void run()
  {
    // Byte code:
    //   0: new 41	java/io/BufferedOutputStream
    //   3: dup
    //   4: aload_0
    //   5: getfield 33	com/applovin/impl/sdk/an:a	Ljava/net/Socket;
    //   8: invokevirtual 47	java/net/Socket:getOutputStream	()Ljava/io/OutputStream;
    //   11: sipush 2048
    //   14: invokespecial 50	java/io/BufferedOutputStream:<init>	(Ljava/io/OutputStream;I)V
    //   17: astore_1
    //   18: aload_0
    //   19: getfield 29	com/applovin/impl/sdk/an:c	Ljava/lang/String;
    //   22: ifnull +73 -> 95
    //   25: aload_0
    //   26: getfield 29	com/applovin/impl/sdk/an:c	Ljava/lang/String;
    //   29: invokevirtual 56	java/lang/String:length	()I
    //   32: ifle +63 -> 95
    //   35: aload_0
    //   36: getfield 29	com/applovin/impl/sdk/an:c	Ljava/lang/String;
    //   39: invokevirtual 60	java/lang/String:getBytes	()[B
    //   42: astore 11
    //   44: aload_1
    //   45: aload_0
    //   46: getfield 27	com/applovin/impl/sdk/an:b	I
    //   49: aload 11
    //   51: arraylength
    //   52: aload_0
    //   53: getfield 31	com/applovin/impl/sdk/an:h	Ljava/lang/String;
    //   56: invokestatic 65	com/applovin/impl/sdk/ak:a	(IILjava/lang/String;)[B
    //   59: invokevirtual 71	java/io/OutputStream:write	([B)V
    //   62: aload_1
    //   63: aload 11
    //   65: invokevirtual 71	java/io/OutputStream:write	([B)V
    //   68: aload_1
    //   69: invokevirtual 74	java/io/OutputStream:flush	()V
    //   72: aload_1
    //   73: ifnull +7 -> 80
    //   76: aload_1
    //   77: invokevirtual 77	java/io/OutputStream:close	()V
    //   80: aload_0
    //   81: getfield 33	com/applovin/impl/sdk/an:a	Ljava/net/Socket;
    //   84: ifnull +10 -> 94
    //   87: aload_0
    //   88: getfield 33	com/applovin/impl/sdk/an:a	Ljava/net/Socket;
    //   91: invokevirtual 78	java/net/Socket:close	()V
    //   94: return
    //   95: aload_1
    //   96: aload_0
    //   97: getfield 27	com/applovin/impl/sdk/an:b	I
    //   100: aload_0
    //   101: getfield 31	com/applovin/impl/sdk/an:h	Ljava/lang/String;
    //   104: invokestatic 81	com/applovin/impl/sdk/ak:a	(ILjava/lang/String;)[B
    //   107: invokevirtual 71	java/io/OutputStream:write	([B)V
    //   110: goto -42 -> 68
    //   113: astore 8
    //   115: aload_0
    //   116: getfield 85	com/applovin/impl/sdk/an:f	Lcom/applovin/sdk/AppLovinLogger;
    //   119: aload_0
    //   120: getfield 88	com/applovin/impl/sdk/an:d	Ljava/lang/String;
    //   123: ldc 90
    //   125: aload 8
    //   127: invokeinterface 96 4 0
    //   132: aload_1
    //   133: sipush 500
    //   136: aload_0
    //   137: getfield 31	com/applovin/impl/sdk/an:h	Ljava/lang/String;
    //   140: invokestatic 81	com/applovin/impl/sdk/ak:a	(ILjava/lang/String;)[B
    //   143: invokevirtual 71	java/io/OutputStream:write	([B)V
    //   146: goto -78 -> 68
    //   149: astore 5
    //   151: aload_0
    //   152: getfield 85	com/applovin/impl/sdk/an:f	Lcom/applovin/sdk/AppLovinLogger;
    //   155: aload_0
    //   156: getfield 88	com/applovin/impl/sdk/an:d	Ljava/lang/String;
    //   159: ldc 98
    //   161: aload 5
    //   163: invokeinterface 96 4 0
    //   168: aload_1
    //   169: ifnull +7 -> 176
    //   172: aload_1
    //   173: invokevirtual 77	java/io/OutputStream:close	()V
    //   176: aload_0
    //   177: getfield 33	com/applovin/impl/sdk/an:a	Ljava/net/Socket;
    //   180: ifnull -86 -> 94
    //   183: aload_0
    //   184: getfield 33	com/applovin/impl/sdk/an:a	Ljava/net/Socket;
    //   187: invokevirtual 78	java/net/Socket:close	()V
    //   190: return
    //   191: astore 6
    //   193: return
    //   194: astore_2
    //   195: aconst_null
    //   196: astore_1
    //   197: aload_1
    //   198: ifnull +7 -> 205
    //   201: aload_1
    //   202: invokevirtual 77	java/io/OutputStream:close	()V
    //   205: aload_0
    //   206: getfield 33	com/applovin/impl/sdk/an:a	Ljava/net/Socket;
    //   209: ifnull +10 -> 219
    //   212: aload_0
    //   213: getfield 33	com/applovin/impl/sdk/an:a	Ljava/net/Socket;
    //   216: invokevirtual 78	java/net/Socket:close	()V
    //   219: aload_2
    //   220: athrow
    //   221: astore 10
    //   223: goto -143 -> 80
    //   226: astore 7
    //   228: goto -52 -> 176
    //   231: astore 4
    //   233: goto -28 -> 205
    //   236: astore_3
    //   237: goto -18 -> 219
    //   240: astore_2
    //   241: goto -44 -> 197
    //   244: astore 5
    //   246: aconst_null
    //   247: astore_1
    //   248: goto -97 -> 151
    //   251: astore 9
    //   253: return
    //
    // Exception table:
    //   from	to	target	type
    //   18	68	113	java/lang/Exception
    //   95	110	113	java/lang/Exception
    //   18	68	149	java/io/IOException
    //   68	72	149	java/io/IOException
    //   95	110	149	java/io/IOException
    //   115	146	149	java/io/IOException
    //   176	190	191	java/io/IOException
    //   0	18	194	finally
    //   76	80	221	java/io/IOException
    //   172	176	226	java/io/IOException
    //   201	205	231	java/io/IOException
    //   205	219	236	java/io/IOException
    //   18	68	240	finally
    //   68	72	240	finally
    //   95	110	240	finally
    //   115	146	240	finally
    //   151	168	240	finally
    //   0	18	244	java/io/IOException
    //   80	94	251	java/io/IOException
  }
}

/* Location:
 * Qualified Name:     com.applovin.impl.sdk.an
 * Java Class Version: 6 (50.0)
 * JD-Core Version:    0.6.1-SNAPSHOT
 */
